Metadata-Version: 2.1
Name: eda-and-clean
Version: 0.1.4
Summary: A package of automation tools for EDA and cleaning
Home-page: https://github.com/aravindganesan88/eda_and_clean
Author: Aravind Ganesan
Author-email: 1988.aravind@gmail.com
License: UNKNOWN
Platform: UNKNOWN
Classifier: Programming Language :: Python :: 3
Classifier: Development Status :: 3 - Alpha
Classifier: License :: OSI Approved :: MIT License
Classifier: Operating System :: OS Independent
Requires-Python: >=3.7
License-File: LICENCE.txt
